{
    "properties": {
        "Z": 2,
        "number_of_atoms_in_molecule": 12,
        "unit_cell_volume": 281.089417,
        "attempted_spg": 30,
        "attempted_wyckoff_position": "2b",
        "site_symmetry_group": "2",
        "spg": 53,
        "lattice_vector_a": [
            3.334721,
            0.0,
            0.0
        ],
        "lattice_vector_b": [
            5.52041814158827e-16,
            9.015527,
            0.0
        ],
        "lattice_vector_c": [
            5.724990490798638e-16,
            5.724990490798638e-16,
            9.349618999999999
        ],
        "cell_vol": 281.0894439554335,
        "a": 3.334721,
        "b": 9.015527,
        "c": 9.349619,
        "alpha": 90.0,
        "beta": 90.0,
        "gamma": 90.0
    },
    "struct_id": "geometry_d5872c7413",
    "input_ref": null,
    "geometry": [
        [
            1.0466280000000003,
            1.6271799999999998,
            -1.0400650000000002,
            "C",
            NaN,
            NaN,
            false
        ],
        [
            1.66736,
            0.9278340000000013,
            2.000000000279556e-06,
            "C",
            NaN,
            NaN,
            false
        ],
        [
            2.288093,
            1.6271799999999998,
            1.0400690000000008,
            "C",
            NaN,
            NaN,
            false
        ],
        [
            2.288093,
            3.025827,
            1.0400690000000008,
            "C",
            NaN,
            NaN,
            false
        ],
        [
            1.6673600000000002,
            3.7251740000000004,
            1.0000000010279564e-06,
            "C",
            NaN,
            NaN,
            false
        ],
        [
            1.0466280000000003,
            3.025827,
            -1.0400650000000002,
            "C",
            NaN,
            NaN,
            false
        ],
        [
            0.5622119999999999,
            1.0815420000000004,
            -1.8517269999999986,
            "H",
            NaN,
            NaN,
            false
        ],
        [
            1.6673599999999997,
            -0.16357799999999875,
            1.0000000010279564e-06,
            "H",
            NaN,
            NaN,
            false
        ],
        [
            2.772509,
            1.0815420000000004,
            1.851731,
            "H",
            NaN,
            NaN,
            false
        ],
        [
            2.7725090000000003,
            3.5714660000000005,
            1.851731,
            "H",
            NaN,
            NaN,
            false
        ],
        [
            1.6673600000000002,
            4.816584000000001,
            1.0000000010279564e-06,
            "H",
            NaN,
            NaN,
            false
        ],
        [
            0.5622119999999999,
            3.5714660000000005,
            -1.8517269999999986,
            "H",
            NaN,
            NaN,
            false
        ],
        [
            2.2880930000000004,
            6.134943000000001,
            3.6347429999999994,
            "C",
            NaN,
            NaN,
            false
        ],
        [
            1.6673610000000008,
            5.4355970000000005,
            4.67481,
            "C",
            NaN,
            NaN,
            false
        ],
        [
            1.0466280000000008,
            6.134943000000001,
            5.7148769999999995,
            "C",
            NaN,
            NaN,
            false
        ],
        [
            1.0466280000000008,
            7.533590000000001,
            5.714877999999999,
            "C",
            NaN,
            NaN,
            false
        ],
        [
            1.667361000000001,
            8.232935,
            4.67481,
            "C",
            NaN,
            NaN,
            false
        ],
        [
            2.288093000000001,
            7.533590000000001,
            3.6347429999999994,
            "C",
            NaN,
            NaN,
            false
        ],
        [
            2.7725090000000003,
            5.589305,
            2.8230809999999993,
            "H",
            NaN,
            NaN,
            false
        ],
        [
            1.6673610000000008,
            4.344186000000001,
            4.67481,
            "H",
            NaN,
            NaN,
            false
        ],
        [
            0.5622120000000013,
            5.589305000000001,
            6.526539,
            "H",
            NaN,
            NaN,
            false
        ],
        [
            0.5622120000000013,
            8.079229,
            6.526539,
            "H",
            NaN,
            NaN,
            false
        ],
        [
            1.667361000000001,
            9.324347,
            4.67481,
            "H",
            NaN,
            NaN,
            false
        ],
        [
            2.7725090000000003,
            8.079229,
            2.8230809999999993,
            "H",
            NaN,
            NaN,
            false
        ]
    ]
}