{
    "properties": {
        "Z": 2,
        "number_of_atoms_in_molecule": 12,
        "unit_cell_volume": 281.648407,
        "attempted_spg": 13,
        "attempted_wyckoff_position": "2b",
        "site_symmetry_group": "-1",
        "spg": 13,
        "lattice_vector_a": [
            3.078111,
            0.0,
            0.0
        ],
        "lattice_vector_b": [
            4.511014039212256e-16,
            7.367045,
            0.0
        ],
        "lattice_vector_c": [
            7.626188812997149e-16,
            -0.9234140000000012,
            12.420231999999999
        ],
        "cell_vol": 281.64841253686035,
        "a": 3.078111,
        "b": 7.367045,
        "c": 12.454511485771732,
        "alpha": 94.25197882233023,
        "beta": 90,
        "gamma": 90,
        "RSF": [
            1.6703300476074219,
            3.249296188354492,
            5.022407054901123,
            6.104097366333008,
            6.50863790512085,
            7.884148120880127,
            10.653397560119629,
            12.818697929382324,
            12.870864868164062,
            11.059142112731934,
            8.206704139709473,
            5.1207122802734375,
            1.2319916486740112,
            2.4530563354492188,
            4.479053974151611,
            7.019697189331055,
            9.10465145111084,
            10.526865005493164,
            11.67200756072998,
            12.154441833496094,
            11.346819877624512,
            9.531838417053223,
            7.3193888664245605,
            4.949136734008789,
            1.2319916486740112,
            2.453056573867798,
            4.4790544509887695,
            7.0196967124938965,
            9.10465145111084,
            10.52686595916748,
            11.67200756072998,
            12.154441833496094,
            11.346819877624512,
            9.531838417053223,
            7.319389343261719,
            4.949137210845947,
            0.6551489233970642,
            2.0945780277252197,
            4.432592868804932,
            6.959638595581055,
            9.07684326171875,
            10.577674865722656,
            11.551944732666016,
            12.0100679397583,
            11.490333557128906,
            9.72140884399414,
            7.328092575073242,
            4.927642345428467
        ],
        "file_path": "benzene_2mpc_0_he_rsf/geometry_c1ce432f8b.json",
        "replica": "init_pool",
        "AP_cluster": 0
    },
    "struct_id": "geometry_c1ce432f8b",
    "input_ref": null,
    "geometry": [
        [
            1.1964000463485718,
            3.3880860805511475,
            1.3233439922332764,
            "C",
            NaN,
            NaN,
            false
        ],
        [
            1.3906869888305664,
            4.716512203216553,
            0.9312329888343811,
            "C",
            NaN,
            NaN,
            false
        ],
        [
            1.7333539724349976,
            5.011958122253418,
            -0.3921490013599396,
            "C",
            NaN,
            NaN,
            false
        ],
        [
            1.8817119598388672,
            3.978959083557129,
            -1.32334303855896,
            "C",
            NaN,
            NaN,
            false
        ],
        [
            1.6874239444732666,
            2.6505320072174072,
            -0.9312329888343811,
            "C",
            NaN,
            NaN,
            false
        ],
        [
            1.3447569608688354,
            2.3550870418548584,
            0.39215201139450073,
            "C",
            NaN,
            NaN,
            false
        ],
        [
            0.9289950132369995,
            3.1575310230255127,
            2.356066942214966,
            "H",
            NaN,
            NaN,
            false
        ],
        [
            1.2748700380325317,
            5.522449970245361,
            1.6580289602279663,
            "H",
            NaN,
            NaN,
            false
        ],
        [
            1.8850070238113403,
            6.048505783081055,
            -0.6983309984207153,
            "H",
            NaN,
            NaN,
            false
        ],
        [
            2.149116039276123,
            4.209514141082764,
            -2.356062889099121,
            "H",
            NaN,
            NaN,
            false
        ],
        [
            1.8032410144805908,
            1.844596028327942,
            -1.6580270528793335,
            "H",
            NaN,
            NaN,
            false
        ],
        [
            1.1931040287017822,
            1.318539023399353,
            0.6983330249786377,
            "H",
            NaN,
            NaN,
            false
        ],
        [
            1.1964000463485718,
            -0.16627000272274017,
            4.886774063110352,
            "C",
            NaN,
            NaN,
            false
        ],
        [
            1.3906869888305664,
            -1.4946969747543335,
            5.278883934020996,
            "C",
            NaN,
            NaN,
            false
        ],
        [
            1.7333539724349976,
            -1.7901420593261719,
            6.602269172668457,
            "C",
            NaN,
            NaN,
            false
        ],
        [
            1.8817119598388672,
            -0.7571430206298828,
            7.5334601402282715,
            "C",
            NaN,
            NaN,
            false
        ],
        [
            1.6874239444732666,
            0.5712839961051941,
            7.141349792480469,
            "C",
            NaN,
            NaN,
            false
        ],
        [
            1.3447569608688354,
            0.8667290210723877,
            5.817965984344482,
            "C",
            NaN,
            NaN,
            false
        ],
        [
            0.9289950132369995,
            0.06428500264883041,
            3.854053020477295,
            "H",
            NaN,
            NaN,
            false
        ],
        [
            1.2748700380325317,
            -2.300632953643799,
            4.552090167999268,
            "H",
            NaN,
            NaN,
            false
        ],
        [
            1.8850070238113403,
            -2.8266890048980713,
            6.908449172973633,
            "H",
            NaN,
            NaN,
            false
        ],
        [
            2.149116039276123,
            -0.9876980185508728,
            8.566182136535645,
            "H",
            NaN,
            NaN,
            false
        ],
        [
            1.8032410144805908,
            1.3772209882736206,
            7.868144989013672,
            "H",
            NaN,
            NaN,
            false
        ],
        [
            1.1931040287017822,
            1.903277039527893,
            5.511785984039307,
            "H",
            NaN,
            NaN,
            false
        ]
    ]
}