{
    "properties": {
        "Z": 2,
        "number_of_atoms_in_molecule": 12,
        "unit_cell_volume": 206.361526,
        "attempted_spg": 158,
        "attempted_wyckoff_position": "2b",
        "site_symmetry_group": "3",
        "spg": 192,
        "lattice_vector_a": [
            6.171705,
            0.0,
            0.0
        ],
        "lattice_vector_b": [
            -3.085853,
            5.344853,
            0.0
        ],
        "lattice_vector_c": [
            0.0,
            0.0,
            6.255871
        ],
        "cell_vol": 206.36151573376546
    },
    "struct_id": "geometry_9740772b71",
    "input_ref": null,
    "geometry": [
        [
            0.236645,
            4.941698,
            0.611877,
            "C",
            NaN,
            NaN,
            false
        ],
        [
            1.312106,
            4.047526,
            0.611877,
            "C",
            NaN,
            NaN,
            false
        ],
        [
            1.075461,
            2.669063,
            0.611877,
            "C",
            NaN,
            NaN,
            false
        ],
        [
            -0.236646,
            2.184773,
            0.611877,
            "C",
            NaN,
            NaN,
            false
        ],
        [
            -1.312107,
            3.078945,
            0.611877,
            "C",
            NaN,
            NaN,
            false
        ],
        [
            -1.075461,
            4.457408,
            0.611877,
            "C",
            NaN,
            NaN,
            false
        ],
        [
            0.421309,
            6.017372,
            0.611877,
            "H",
            NaN,
            NaN,
            false
        ],
        [
            2.335999,
            4.425438,
            0.611877,
            "H",
            NaN,
            NaN,
            false
        ],
        [
            1.91469,
            1.971302,
            0.611877,
            "H",
            NaN,
            NaN,
            false
        ],
        [
            -0.42131,
            1.109099,
            0.611877,
            "H",
            NaN,
            NaN,
            false
        ],
        [
            -2.336,
            2.701032,
            0.611877,
            "H",
            NaN,
            NaN,
            false
        ],
        [
            -1.91469,
            5.155169,
            0.611877,
            "H",
            NaN,
            NaN,
            false
        ],
        [
            -1.075461,
            2.669063,
            3.739811,
            "C",
            NaN,
            NaN,
            false
        ],
        [
            0.236645,
            2.184773,
            3.739811,
            "C",
            NaN,
            NaN,
            false
        ],
        [
            1.312106,
            3.078945,
            3.739811,
            "C",
            NaN,
            NaN,
            false
        ],
        [
            1.075461,
            4.457408,
            3.739811,
            "C",
            NaN,
            NaN,
            false
        ],
        [
            -0.236646,
            4.941699,
            3.739811,
            "C",
            NaN,
            NaN,
            false
        ],
        [
            -1.312107,
            4.047526,
            3.739811,
            "C",
            NaN,
            NaN,
            false
        ],
        [
            -1.91469,
            1.971302,
            3.739811,
            "H",
            NaN,
            NaN,
            false
        ],
        [
            0.42131,
            1.109099,
            3.739811,
            "H",
            NaN,
            NaN,
            false
        ],
        [
            2.335999,
            2.701032,
            3.739811,
            "H",
            NaN,
            NaN,
            false
        ],
        [
            1.91469,
            5.155169,
            3.739811,
            "H",
            NaN,
            NaN,
            false
        ],
        [
            -0.421311,
            6.017372,
            3.739811,
            "H",
            NaN,
            NaN,
            false
        ],
        [
            -2.336,
            4.425438,
            3.739811,
            "H",
            NaN,
            NaN,
            false
        ]
    ]
}