{
    "properties": {
        "Z": 2,
        "number_of_atoms_in_molecule": 12,
        "unit_cell_volume": 252.276962,
        "attempted_spg": 115,
        "attempted_wyckoff_position": "2g",
        "site_symmetry_group": "mm2",
        "spg": 115,
        "lattice_vector_a": [
            3.118353,
            0.0,
            0.0
        ],
        "lattice_vector_b": [
            5.507531795644242e-16,
            8.994482,
            0.0
        ],
        "lattice_vector_c": [
            5.507531795644242e-16,
            5.507531795644241e-16,
            8.994482
        ],
        "cell_vol": 252.27696065525046,
        "a": 3.118353,
        "b": 8.994482,
        "c": 8.994482,
        "alpha": 90.0,
        "beta": 90.0,
        "gamma": 90.0
    },
    "struct_id": "geometry_7059f36499",
    "input_ref": null,
    "geometry": [
        [
            0.8788330000000004,
            1.2112190000000003,
            5.196565,
            "C",
            NaN,
            NaN,
            false
        ],
        [
            0.8788330000000003,
            1.2112190000000003,
            3.797917,
            "C",
            NaN,
            NaN,
            false
        ],
        [
            0.8788330000000002,
            1.8973281408638058e-16,
            3.098572,
            "C",
            NaN,
            NaN,
            false
        ],
        [
            0.8788330000000001,
            -1.2112179999999997,
            3.797917,
            "C",
            NaN,
            NaN,
            false
        ],
        [
            0.8788330000000002,
            -1.2112179999999997,
            5.196565,
            "C",
            NaN,
            NaN,
            false
        ],
        [
            0.8788330000000003,
            3.610203654780435e-16,
            5.89591,
            "C",
            NaN,
            NaN,
            false
        ],
        [
            0.8788330000000004,
            2.1564460000000003,
            5.742203,
            "H",
            NaN,
            NaN,
            false
        ],
        [
            0.8788330000000003,
            2.156446,
            3.252279,
            "H",
            NaN,
            NaN,
            false
        ],
        [
            0.8788330000000001,
            1.2290310346883005e-16,
            2.00716,
            "H",
            NaN,
            NaN,
            false
        ],
        [
            0.8788330000000001,
            -2.156445,
            3.252279,
            "H",
            NaN,
            NaN,
            false
        ],
        [
            0.8788330000000002,
            -2.1564449999999997,
            5.742203,
            "H",
            NaN,
            NaN,
            false
        ],
        [
            0.8788330000000004,
            4.2785001486325406e-16,
            6.987321,
            "H",
            NaN,
            NaN,
            false
        ],
        [
            2.2395200000000006,
            5.196565,
            -1.2112189999999998,
            "C",
            NaN,
            NaN,
            false
        ],
        [
            2.2395200000000006,
            3.797917,
            -1.2112189999999998,
            "C",
            NaN,
            NaN,
            false
        ],
        [
            2.2395200000000006,
            3.098572,
            -9.999999992515995e-07,
            "C",
            NaN,
            NaN,
            false
        ],
        [
            2.2395200000000006,
            3.797917,
            1.2112169999999995,
            "C",
            NaN,
            NaN,
            false
        ],
        [
            2.2395200000000006,
            5.196564,
            1.2112169999999995,
            "C",
            NaN,
            NaN,
            false
        ],
        [
            2.2395200000000006,
            5.89591,
            -2.000000000279556e-06,
            "C",
            NaN,
            NaN,
            false
        ],
        [
            2.2395200000000006,
            5.742202999999999,
            -2.156446,
            "H",
            NaN,
            NaN,
            false
        ],
        [
            2.23952,
            3.252279,
            -2.156446,
            "H",
            NaN,
            NaN,
            false
        ],
        [
            2.2395200000000006,
            2.00716,
            -9.999999992515995e-07,
            "H",
            NaN,
            NaN,
            false
        ],
        [
            2.2395200000000006,
            3.2522790000000006,
            2.1564440000000005,
            "H",
            NaN,
            NaN,
            false
        ],
        [
            2.2395200000000006,
            5.742203,
            2.1564440000000005,
            "H",
            NaN,
            NaN,
            false
        ],
        [
            2.2395200000000006,
            6.987321,
            -9.999999992515995e-07,
            "H",
            NaN,
            NaN,
            false
        ]
    ]
}