{
    "properties": {
        "lattice_vector_a": [
            8.084596,
            0.0,
            0.0
        ],
        "lattice_vector_b": [
            0.0,
            8.338,
            0.0
        ],
        "lattice_vector_c": [
            2.729451,
            0.0,
            3.062083
        ],
        "unit_cell_volume": 206.41305973077618,
        "cell_vol": 206.41305973077618,
        "spg": 4,
        "molecule_harris_info": [
            [
                -10.42238489754367,
                -52.54754246981504,
                -0.06208260437118852,
                4.005922521682495,
                8.493888770012145,
                2.6245769843696913,
                false
            ],
            [
                -169.57753882647668,
                -127.45305750977687,
                179.93800742442065,
                6.808125982893274,
                4.324888111429011,
                0.43749681523347156,
                false
            ]
        ],
        "harris_energy": -16713.553884873,
        "rcd": [
            [
                [
                    -2.3713243223916485,
                    1.7582189527804817,
                    2.8481119230470684
                ],
                [
                    0.9999999403953552,
                    1.0000001192092896,
                    1.0000001192092896
                ]
            ],
            [
                [
                    2.3713243411884157,
                    -1.7582189788125784,
                    -2.848111940901177
                ],
                [
                    1.0,
                    1.0000001192092896,
                    1.0
                ]
            ],
            [
                [
                    2.5651067814483604,
                    -0.8505375484090677,
                    4.16659484790706
                ],
                [
                    0.3169034421443939,
                    -0.9096561074256897,
                    -0.4072474539279938
                ]
            ],
            [
                [
                    -4.20076628575173,
                    -2.6226699685718997,
                    -0.3726513842990321
                ],
                [
                    0.31690341234207153,
                    -0.9096561074256897,
                    -0.4072474241256714
                ]
            ],
            [
                [
                    3.8212816882939444,
                    3.9014433702292024,
                    0.43904511332889296
                ],
                [
                    0.31690338253974915,
                    -0.9096560478210449,
                    -0.4072474241256714
                ]
            ],
            [
                [
                    -2.944591378906146,
                    2.1293109500663703,
                    -4.100201118877199
                ],
                [
                    0.316903293132782,
                    -0.9096560478210449,
                    -0.4072473347187042
                ]
            ],
            [
                [
                    4.936431124434491,
                    -2.6087564905401504,
                    1.318482890005786
                ],
                [
                    0.31690338253974915,
                    -0.9096561074256897,
                    -0.4072474241256714
                ]
            ],
            [
                [
                    -1.8294419427655992,
                    -4.380888910702983,
                    -3.220763342200306
                ],
                [
                    0.316903293132782,
                    -0.9096561074256897,
                    -0.40724730491638184
                ]
            ],
            [
                [
                    -1.2561749322834714,
                    -4.751980970598478,
                    3.7275497927794525
                ],
                [
                    1.0,
                    1.0000001192092896,
                    1.0
                ]
            ],
            [
                [
                    1.256174972418672,
                    4.751980962176913,
                    -3.7275498493142907
                ],
                [
                    1.0,
                    1.0000001192092896,
                    1.0
                ]
            ],
            [
                [
                    -1.1151493620876138,
                    6.5101998511045975,
                    -0.8794378832817151
                ],
                [
                    1.0,
                    1.0000001192092896,
                    1.0
                ]
            ],
            [
                [
                    1.115149366560115,
                    -6.510199776633086,
                    0.8794378475414522
                ],
                [
                    1.0,
                    1.0000001192092896,
                    1.0
                ]
            ],
            [
                [
                    1.4499573857345567,
                    5.6596623147579175,
                    3.2871570100369327
                ],
                [
                    0.31690338253974915,
                    -0.9096561074256897,
                    -0.4072474241256714
                ]
            ],
            [
                [
                    -5.315915681465533,
                    3.887529894595085,
                    -1.2520892221691595
                ],
                [
                    0.316903293132782,
                    -0.9096561074256897,
                    -0.4072472155094147
                ]
            ],
            [
                [
                    6.192606054635735,
                    2.1432244431420253,
                    -2.4090668852578263
                ],
                [
                    0.31690341234207153,
                    -0.9096561074256897,
                    -0.4072474241256714
                ]
            ],
            [
                [
                    -0.5732670125643551,
                    0.3710920229791931,
                    -6.948313117463918
                ],
                [
                    0.31690332293510437,
                    -0.9096561074256897,
                    -0.4072473645210266
                ]
            ]
        ],
        "file_path": "target1_2mpc_0_he_rcd/target1_2mpc_11a88ccc80.json",
        "replica": "init_pool",
        "AP_cluster": 8
    },
    "struct_id": "target1_2mpc_11a88ccc80",
    "input_ref": null,
    "geometry": [
        [
            5.101517200469971,
            9.970946311950684,
            2.7796010971069336,
            "O",
            NaN,
            NaN,
            false
        ],
        [
            5.0201897621154785,
            9.139562606811523,
            1.6771939992904663,
            "C",
            NaN,
            NaN,
            false
        ],
        [
            5.66953182220459,
            9.41094970703125,
            0.8546980023384094,
            "H",
            NaN,
            NaN,
            false
        ],
        [
            4.106327056884766,
            8.171168327331543,
            1.9490489959716797,
            "C",
            NaN,
            NaN,
            false
        ],
        [
            3.2325220108032227,
            6.942179203033447,
            1.745129942893982,
            "C",
            NaN,
            NaN,
            false
        ],
        [
            3.7724969387054443,
            5.993764877319336,
            1.6277879476547241,
            "H",
            NaN,
            NaN,
            false
        ],
        [
            2.484534978866577,
            7.021646022796631,
            0.9457150101661682,
            "H",
            NaN,
            NaN,
            false
        ],
        [
            2.67057204246521,
            7.205695152282715,
            3.205152988433838,
            "C",
            NaN,
            NaN,
            false
        ],
        [
            2.8845949172973633,
            6.408377170562744,
            3.928670883178711,
            "H",
            NaN,
            NaN,
            false
        ],
        [
            1.598992943763733,
            7.439857006072998,
            3.246722936630249,
            "H",
            NaN,
            NaN,
            false
        ],
        [
            3.6038269996643066,
            8.4065523147583,
            3.25813889503479,
            "C",
            NaN,
            NaN,
            false
        ],
        [
            4.225957870483398,
            9.511659622192383,
            3.746553897857666,
            "C",
            NaN,
            NaN,
            false
        ],
        [
            4.209461212158203,
            10.094171524047852,
            4.658819198608398,
            "H",
            NaN,
            NaN,
            false
        ],
        [
            5.712530136108398,
            5.801945209503174,
            0.28248199820518494,
            "O",
            NaN,
            NaN,
            false
        ],
        [
            5.793857097625732,
            4.9705610275268555,
            1.384889006614685,
            "C",
            NaN,
            NaN,
            false
        ],
        [
            5.144515037536621,
            5.241950988769531,
            2.2073850631713867,
            "H",
            NaN,
            NaN,
            false
        ],
        [
            6.707719802856445,
            4.002167224884033,
            1.1130340099334717,
            "C",
            NaN,
            NaN,
            false
        ],
        [
            7.581524848937988,
            2.7731781005859375,
            1.3169519901275635,
            "C",
            NaN,
            NaN,
            false
        ],
        [
            7.041550159454346,
            1.8247640132904053,
            1.4342950582504272,
            "H",
            NaN,
            NaN,
            false
        ],
        [
            8.329511642456055,
            2.8526461124420166,
            2.116368055343628,
            "H",
            NaN,
            NaN,
            false
        ],
        [
            8.143474578857422,
            3.0366950035095215,
            -0.1430709958076477,
            "C",
            NaN,
            NaN,
            false
        ],
        [
            7.929451942443848,
            2.2393760681152344,
            -0.8665879964828491,
            "H",
            NaN,
            NaN,
            false
        ],
        [
            9.21505355834961,
            3.2708590030670166,
            -0.18464000523090363,
            "H",
            NaN,
            NaN,
            false
        ],
        [
            7.210218906402588,
            4.237552165985107,
            -0.19605599343776703,
            "C",
            NaN,
            NaN,
            false
        ],
        [
            6.5880889892578125,
            5.342659950256348,
            -0.6844710111618042,
            "C",
            NaN,
            NaN,
            false
        ],
        [
            6.604587078094482,
            5.9251708984375,
            -1.596735954284668,
            "H",
            NaN,
            NaN,
            false
        ]
    ]
}